tpds_extension/avnet_iotconnect/extension.yaml
tpds_extension/avnet_iotconnect/setup.py
tpds_extension/avnet_iotconnect/version.py
tpds_extension/avnet_iotconnect/TrustFlex/Avnet IoTConnect.ipynb
tpds_extension/avnet_iotconnect/TrustFlex/EBV-IoT Secure Kit v1.0_template.json
tpds_extension/avnet_iotconnect/TrustFlex/cust_def_1_signer.c
tpds_extension/avnet_iotconnect/TrustFlex/cust_def_1_signer.h
tpds_extension/avnet_iotconnect/TrustFlex/cust_def_2_device.c
tpds_extension/avnet_iotconnect/TrustFlex/cust_def_2_device.h
tpds_extension/avnet_iotconnect/TrustFlex/firmware.zip
tpds_extension/avnet_iotconnect/TrustFlex/assets/Custom PKI Avnet.md
tpds_extension/avnet_iotconnect/TrustFlex/assets/avnet_iotconnect_trust.ui
tpds_extension/avnet_iotconnect/TrustFlex/assets/shield.ico
tpds_extension/avnet_iotconnect/TrustFlex/assets/images/Avnet.png
tpds_extension/avnet_iotconnect/TrustFlex/assets/images/assets_custompki_avnet.png
tpds_extension/avnet_iotconnect/TrustFlex/assets/images/board_stack.png
tpds_extension/avnet_iotconnect/TrustFlex/assets/images/c-snippet.png
tpds_extension/avnet_iotconnect/TrustFlex/assets/images/help_check.png
tpds_extension/avnet_iotconnect/TrustFlex/assets/images/help_copy.png
tpds_extension/avnet_iotconnect/TrustFlex/assets/images/help_cpid.png
tpds_extension/avnet_iotconnect/TrustFlex/assets/images/help_createca1.png
tpds_extension/avnet_iotconnect/TrustFlex/assets/images/help_createca2.png
tpds_extension/avnet_iotconnect/TrustFlex/assets/images/help_createdev.png
tpds_extension/avnet_iotconnect/TrustFlex/assets/images/help_dialog1.png
tpds_extension/avnet_iotconnect/TrustFlex/assets/images/help_dialog2.png
tpds_extension/avnet_iotconnect/TrustFlex/assets/images/help_iotconnect.png
tpds_extension/avnet_iotconnect/TrustFlex/assets/images/help_register.png
tpds_extension/avnet_iotconnect/TrustFlex/assets/images/help_sn.png
tpds_extension/avnet_iotconnect/TrustFlex/assets/images/help_testOTA.png
tpds_extension_avnet_iotconnect-2.2.4.dist-info/METADATA
tpds_extension_avnet_iotconnect-2.2.4.dist-info/WHEEL
tpds_extension_avnet_iotconnect-2.2.4.dist-info/top_level.txt
tpds_extension_avnet_iotconnect-2.2.4.dist-info/RECORD
