Metadata-Version: 2.1
Name: tpds-extension-avnet-iotconnect
Version: 2.2.4
Summary: Microchip(SPG) Trust Platform Usecase for Avnet IoTConnect
Home-page: https://www.microchip.com/TrustPlatform
Author: Microchip Technology
Author-email: SPG.Tools@microchip.com
Classifier: License :: Other/Proprietary License
Classifier: Development Status :: 4 - Beta
Classifier: Programming Language :: Python :: 3
Classifier: Operating System :: OS Independent
Requires-Python: >=3.6
